eorcalc/__init__.py
eorcalc/iondiff.py
eorcalc/ioninti.py
eorcalc/ioninti_gpu.py
eorcalc/powerspec.py
eorcalc/reion_field.py
eorcalc/special.py
eorcalc-0.1.2.dist-info/licenses/LICENSE
eorcalc-0.1.2.dist-info/METADATA
eorcalc-0.1.2.dist-info/WHEEL
eorcalc-0.1.2.dist-info/top_level.txt
eorcalc-0.1.2.dist-info/RECORD
