Metadata-Version: 2.4
Name: eorcalc
Version: 0.1.2
Summary: GPU-accelerated reionization field calculator with power spectrum analysis for the Epoch of Reionization
Author-email: Hajime Hinata <onmyojiflow@gmail.com>
License: MIT
Project-URL: Homepage, https://github.com/SOYONAOC/EoRCaLC
Project-URL: Repository, https://github.com/SOYONAOC/EoRCaLC
Project-URL: Bug Reports, https://github.com/SOYONAOC/EoRCaLC/issues
Project-URL: Documentation, https://github.com/SOYONAOC/EoRCaLC#readme
Keywords: astrophysics,cosmology,ionization,power spectrum,diffusion,reionization,EoR,GPU,ionization field,optical depth
Classifier: Development Status :: 3 - Alpha
Classifier: Intended Audience :: Science/Research
Classifier: License :: OSI Approved :: MIT License
Classifier: Operating System :: OS Independent
Classifier: Programming Language :: Python :: 3
Classifier: Programming Language :: Python :: 3.8
Classifier: Programming Language :: Python :: 3.9
Classifier: Programming Language :: Python :: 3.10
Classifier: Programming Language :: Python :: 3.11
Classifier: Programming Language :: Python :: 3.12
Classifier: Topic :: Scientific/Engineering :: Astronomy
Classifier: Topic :: Scientific/Engineering :: Physics
Requires-Python: >=3.8
License-File: LICENSE
Requires-Dist: numpy>=1.20.0
Requires-Dist: scipy>=1.6.0
Requires-Dist: pandas>=1.3.0
Requires-Dist: astropy>=4.0
Requires-Dist: filelock>=3.0.0
Requires-Dist: camb>=1.3.0
Requires-Dist: massfunc>=0.0.10
Requires-Dist: cosfunc>=0.1.0
Requires-Dist: xxiop>=0.1.0
Requires-Dist: cupy-cuda12x>=12.0.0
Provides-Extra: dev
Requires-Dist: pytest>=7.0; extra == "dev"
Requires-Dist: pytest-cov>=3.0; extra == "dev"
Requires-Dist: black>=22.0; extra == "dev"
Requires-Dist: flake8>=4.0; extra == "dev"
Requires-Dist: mypy>=0.950; extra == "dev"
Requires-Dist: ipython>=8.0; extra == "dev"
Requires-Dist: jupyter>=1.0; extra == "dev"
Provides-Extra: test
Requires-Dist: pytest>=7.0; extra == "test"
Requires-Dist: pytest-cov>=3.0; extra == "test"
Provides-Extra: gpu-cuda11
Requires-Dist: cupy-cuda11x>=11.0.0; extra == "gpu-cuda11"
Dynamic: license-file
